{
  "name": "Daniel Payne",
  "years": "February 24, 1811 – November 2, 1893",
  "title": "Bishop & Educator",
  "bio": "African Methodist Episcopal bishop and educator who became the first Black president of a university in the United States (Wilberforce University, 1863). Born free in Charleston, South Carolina, he was forced to close his school for Black children when South Carolina outlawed educating enslaved people.",
  "faith": "Payne believed passionately that education was essential to the spiritual and social advancement of Black Americans. As AME bishop, he reformed the denomination's education standards for clergy. He purchased Wilberforce University from the Methodist Episcopal Church and shaped it into a center of Black intellectual and spiritual life.",
  "videos": [],
  "sources": [
    {"type": "wikipedia", "title": "Daniel Payne — Wikipedia", "url": "https://en.wikipedia.org/wiki/Daniel_Payne"}
  ],
  "slug": "daniel-payne",
  "tagline": "First Black university president in America — AME bishop and educator",
  "image": "/images/bios/daniel-payne.jpg",
  "imageAttribution": {"source": "Wikimedia Commons", "license": "Public Domain"}
}
