{
    "name": "Martyn Lloyd-Jones",
    "years": "December 20, 1899 – March 1, 1981",
    "title": "Preacher & Pastor",
    "bio": "Welsh Protestant minister who left a promising career in medicine to preach. Served as pastor of Westminster Chapel in London for 30 years, becoming one of the most influential preachers of the 20th century.",
    "faith": "Lloyd-Jones was a passionate defender of expository preaching and Reformed theology. His multi-volume studies on Romans and Ephesians, and his book Preaching and Preachers, have shaped generations of pastors. He emphasized the necessity of experiencing God's power, not merely knowing about Him.",
    "videos": [],
    "sources": [
        {
            "type": "wikipedia",
            "title": "Lloyd-Jones — Wikipedia",
            "url": "https://en.wikipedia.org/wiki/Martyn_Lloyd-Jones",
            "note": "Welsh preacher at Westminster Chapel"
        },
        {
            "type": "sermon",
            "title": "Sermons — MLJ Trust",
            "url": "https://www.mljtrust.org/sermons/",
            "note": "Archive of over 1,600 sermons by Lloyd-Jones from his years at Westminster Chapel, London"
        },
        {
            "type": "book",
            "title": "D. Martyn Lloyd-Jones: The First Forty Years / The Fight of Faith by Iain Murray",
            "note": "Definitive two-volume biography by Iain Murray, published by Banner of Truth Trust"
        }
    ],
    "slug": "martyn-lloyd-jones",
    "tagline": "The Doctor who left medicine to preach the Great Physician",
    "image": "/images/bios/martyn-lloyd-jones.jpg",
    "imageAttribution": {
        "source": "",
        "license": ""
    }
}
